dutch_text_analytics/__init__.py
dutch_text_analytics/demo_data.py
dutch_text_analytics/textanalytics.py
dutch_text_analytics-0.1.2.dist-info/LICENSE
dutch_text_analytics-0.1.2.dist-info/METADATA
dutch_text_analytics-0.1.2.dist-info/WHEEL
dutch_text_analytics-0.1.2.dist-info/top_level.txt
dutch_text_analytics-0.1.2.dist-info/RECORD
