Metadata-Version: 2.1
Name: dutch-text-analytics
Version: 0.1.2
Summary: Dutch Text Analytics is a versatile toolkit designed to facilitate the exploration, execution, and validation of a diverse range of Natural Language Processing (NLP) tasks specifically tailored for the Dutch language. This repository provides a comprehensive set of tools, including code examples, scripts, and resources, to enhance and streamline your Dutch NLP projects.
Home-page: UNKNOWN
License: UNKNOWN
Platform: UNKNOWN
Requires-Dist: gensim (>=4.0.0)
Requires-Dist: ipywidgets (>=7.6.0)
Requires-Dist: jupyter (>=1.0.0)
Requires-Dist: keybert (>=0.4.0)
Requires-Dist: nltk (>=3.5.0)
Requires-Dist: numpy (>=1.18.0)
Requires-Dist: openpyxl (>=3.0.0)
Requires-Dist: pandas (>=1.0.0)
Requires-Dist: python-Levenshtein (>=0.12.0)
Requires-Dist: scikit-learn (>=0.24.0)
Requires-Dist: scipy (>=1.4.0)
Requires-Dist: sent2vec (>=0.2.0)
Requires-Dist: sentence-transformers (>=2.0.0)
Requires-Dist: spacy (>=3.0.0)
Requires-Dist: torch (>=1.8.0)
Requires-Dist: transformers (>=4.5.0)
